compose_x_common/__init__.py
compose_x_common/aws/__init__.py
compose_x_common/aws/acm.py
compose_x_common/aws/application_autoscaling.py
compose_x_common/aws/aps.py
compose_x_common/aws/arns.py
compose_x_common/aws/cloudmap.py
compose_x_common/aws/codeguru_profiler.py
compose_x_common/aws/cognito_userpool.py
compose_x_common/aws/dynamodb.py
compose_x_common/aws/ec2.py
compose_x_common/aws/ecr/__init__.py
compose_x_common/aws/ecr/images.py
compose_x_common/aws/ecr/repositories.py
compose_x_common/aws/ecs/__init__.py
compose_x_common/aws/ecs/instances.py
compose_x_common/aws/ecs/services.py
compose_x_common/aws/ecs/tasks.py
compose_x_common/aws/efs.py
compose_x_common/aws/elasticache.py
compose_x_common/aws/elasticloadbalancing.py
compose_x_common/aws/glue/__init__.py
compose_x_common/aws/iam.py
compose_x_common/aws/kafka.py
compose_x_common/aws/kinesis.py
compose_x_common/aws/kms.py
compose_x_common/aws/msk.py
compose_x_common/aws/neptune.py
compose_x_common/aws/opensearch.py
compose_x_common/aws/rds.py
compose_x_common/aws/resourcegroupstaggingapi.py
compose_x_common/aws/route53.py
compose_x_common/aws/s3.py
compose_x_common/aws/secrets_manager.py
compose_x_common/aws/sns.py
compose_x_common/aws/sqs.py
compose_x_common/aws/ssm_parameter.py
compose_x_common/aws/vpc.py
compose_x_common/aws/wafv2.py
compose_x_common/compose_x_common.py
compose_x_common-1.4.11.dist-info/AUTHORS.rst
compose_x_common-1.4.11.dist-info/LICENSE
compose_x_common-1.4.11.dist-info/METADATA
compose_x_common-1.4.11.dist-info/WHEEL
compose_x_common-1.4.11.dist-info/RECORD
