Metadata-Version: 2.3
Name: compose_x_common
Version: 1.4.11
Summary: Common Library for Compose-X Projects
License: MPL-2.0
Keywords: compose-x,docker,compose
Author: John Preston
Author-email: john@compose-x.io
Maintainer: John Preston
Maintainer-email: john@compose-x.io
Requires-Python: >=3.8,<4.0
Classifier: Development Status :: 5 - Production/Stable
Classifier: Intended Audience :: Developers
Classifier: License :: OSI Approved
Classifier: Natural Language :: English
Classifier: Programming Language :: Python :: 3
Classifier: Programming Language :: Python :: 3.8
Classifier: Programming Language :: Python :: 3.9
Classifier: Programming Language :: Python :: 3.10
Classifier: Programming Language :: Python :: 3.11
Classifier: Programming Language :: Python :: 3.12
Classifier: Programming Language :: Python :: 3.13
Requires-Dist: boto3 (>=1.26,<2.0)
Requires-Dist: flatdict (>=4.0.1,<5.0.0)
Requires-Dist: python-dateutil (>=2.8.2,<3.0.0)
Project-URL: Repository, https://github.com/compose-x/compose-x-common-libs/
